{
  "title": "Deflate",
  "path": "compression/deflate.vitl",
  "family": "compression",
  "family_key": "compression",
  "kind": "public stdlib surface",
  "line_count": 115,
  "purpose": "`compression/deflate.vitl` is a public stdlib surface inside the `compression` family. It should be read as one focused slice of the broader family responsibility: Algorithms and interfaces for compacting data: huffman, lz, deflate, brotli, stats, and shared compression interfaces.",
  "use_cases": [
    "A report archive can be built in memory, then compressed before emission.",
    "A transport layer can separate serialization from compression instead of mixing both in one procedure."
  ],
  "procedures": [
    "_slice_text",
    "deflate_version",
    "deflate_ready",
    "deflate_manifest",
    "deflate_health",
    "deflate_summary",
    "compress_deflate",
    "decompress_deflate",
    "compress_zlib",
    "decompress_zlib",
    "compress_gzip",
    "decompress_gzip",
    "deflate_selftest"
  ],
  "forms": [
    "DeflateContext",
    "DeflateManifest",
    "DeflateHealth",
    "DeflateSummary"
  ],
  "picks": [],
  "constants": [
    "Z_NO_COMPRESSION",
    "Z_FAST_COMPRESSION",
    "Z_DEFAULT_COMPRESSION",
    "Z_BEST_COMPRESSION",
    "Z_DEFAULT_STRATEGY",
    "Z_RLE"
  ],
  "imports": [],
  "siblings": [
    "compression/algorithms.vitl",
    "compression/brotli.vitl",
    "compression/huffman.vitl",
    "compression/interface.vitl",
    "compression/lz.vitl",
    "compression/stats.vitl",
    "compression/tests/smoke.vitl",
    "compression.vitl"
  ]
}
