{
  "title": "Users",
  "path": "kernel/users.vitl",
  "family": "kernel",
  "family_key": "kernel",
  "kind": "public stdlib surface",
  "line_count": 330,
  "purpose": "`kernel/users.vitl` is a public stdlib surface inside the `kernel` family. It should be read as one focused slice of the broader family responsibility: System-facing runtime helpers such as process, scheduler, threads, sync, users, signals, network, device, and memory.",
  "use_cases": [
    "A service manager may use scheduler, process, and signals while keeping policy in separate code.",
    "A network-facing runtime should explain why it depends on kernel surfaces instead of lighter families."
  ],
  "procedures": [
    "getuid",
    "geteuid",
    "setuid",
    "seteuid",
    "getgid",
    "getegid",
    "setgid",
    "setegid",
    "getgroups",
    "setgroups",
    "getpid",
    "getppid",
    "getpgid",
    "setpgid",
    "getpgrp",
    "setsid",
    "getsid",
    "getpwuid",
    "getpwnam",
    "getgrgid",
    "getgrnam",
    "getrlimit",
    "setrlimit",
    "getrlimit_cpu",
    "setrlimit_cpu",
    "getrlimit_fsize",
    "setrlimit_fsize",
    "getrlimit_nofile",
    "setrlimit_nofile",
    "getenv",
    "setenv",
    "unsetenv",
    "environ",
    "clearenv",
    "getpriority",
    "setpriority",
    "getrusage",
    "get_login",
    "get_username",
    "get_home_dir",
    "get_shell",
    "is_root",
    "access",
    "faccessat",
    "eaccess",
    "initgroups"
  ],
  "forms": [
    "PasswdEntry",
    "GroupEntry",
    "RlimitEntry"
  ],
  "picks": [],
  "constants": [
    "RLIMIT_CPU",
    "RLIMIT_FSIZE",
    "RLIMIT_DATA",
    "RLIMIT_STACK",
    "RLIMIT_CORE",
    "RLIMIT_RSS",
    "RLIMIT_NPROC",
    "RLIMIT_NOFILE",
    "RLIMIT_MEMLOCK",
    "RLIMIT_AS",
    "RLIM_INFINITY"
  ],
  "imports": [],
  "exports": [
    "*"
  ],
  "siblings": [
    "kernel/device.vitl",
    "kernel/fileio.vitl",
    "kernel/interrupt.vitl",
    "kernel/memory.vitl",
    "kernel/network.vitl",
    "kernel/process.vitl",
    "kernel/scheduler.vitl",
    "kernel/signals.vitl"
  ]
}
